polytorch/__init__.py
polytorch/data.py
polytorch/embedding.py
polytorch/enums.py
polytorch/loss.py
polytorch/metrics.py
polytorch/modules.py
polytorch/plots.py
polytorch/util.py
polytorch-0.1.4.dist-info/LICENSE
polytorch-0.1.4.dist-info/METADATA
polytorch-0.1.4.dist-info/WHEEL
polytorch-0.1.4.dist-info/RECORD
