Metadata-Version: 2.3
Name: PolyTorch
Version: 0.1.4
Summary: Embeddings and loss functions for different data types.
License: Apache-2.0
Keywords: pytorch,deep learning,command-line interface
Author: Robert Turnbull
Author-email: robert.turnbull@unimelb.edu.au
Requires-Python: >=3.10,<4.0
Classifier: Intended Audience :: Science/Research
Classifier: License :: OSI Approved :: Apache Software License
Classifier: Programming Language :: Python :: 3
Classifier: Programming Language :: Python :: 3.10
Classifier: Programming Language :: Python :: 3.11
Classifier: Programming Language :: Python :: 3.12
Classifier: Programming Language :: Python :: 3.13
Classifier: Topic :: Scientific/Engineering :: Artificial Intelligence
Classifier: Topic :: Software Development :: Libraries :: Python Modules
Requires-Dist: attrs (>=19)
Requires-Dist: hierarchicalsoftmax (>=1.4.1)
Requires-Dist: kaleido (==0.2.1)
Requires-Dist: plotly (>=5.15.0)
Requires-Dist: scikit-learn (>=1.0.2)
Requires-Dist: torch (>=1.10.2)
Project-URL: Documentation, https://rbturnbull.github.io/polytorch
Project-URL: Homepage, https://github.com/rbturnbull/polytorch/
Project-URL: Repository, https://github.com/rbturnbull/polytorch/
